{"id":"some-request-id","site":{"page":"prebid.org","inventorypartnerdomain":"any-domain"},"imp":[{"id":"some-impression-id","banner":{"format":[{"w":300,"h":600}]},"ext":{"prebid":{"bidder":{"appnexus":{"placementId":12883451},"rubicon":{"accountId":1,"siteId":2,"zoneId":3}},"is_rewarded_inventory":1}},"refresh":{"count":10}}],"regs":{"ext":{"gdpr":1,"us_privacy":"1YYY"}},"user":{"ext":{"consent":"some-consent-string","eids":[{"source":"source","uids":[{"id":"1","atype":1,"ext":{}},{"id":"1","atype":1,"ext":{}}],"ext":{}}]}},"source":{"ext":{"schain":{"complete":1,"nodes":[{"asi":"whatever.com","sid":"1234","rid":"123-456-7890","hp":1}],"ver":"2.0"}}},"ext":{},"cattax":20,"acat":["any-acat"]}